{
  "ui": {
    "pipelines": "Pipelines",
    "scan_rate": "Scan rate (A/g)",
    "import_eis": "Importar EIS para raw",
    "import_cycling": "Importar Ciclagem para processed",
    "interactive_charts": "Gráficos Interativos",
    "run_eis": "Rodar Pipeline EIS",
    "run_cycling": "Rodar Pipeline Ciclagem",
    "run_both": "Rodar Ambos",
    "run_drt": "Rodar Pipeline DRT",
    "apply_preset": "Aplicar preset",
    "reset_drt": "Reset DRT",
    "preset_drt": "Preset DRT",
    "lambda_drt": "λ DRT",
    "n_taus": "n_taus",
    "drt_presets_hint": "Rápido:30 | Balanceado:50 | Alta:80",
    "theme": "Tema",
    "light": "Claro",
    "dark": "Escuro",
    "system": "Sistema",
    "language": "Idioma",
    "fast": "Rápido",
    "balanced": "Balanceado",
    "high_resolution": "Alta resolução",
    "spectrum": "Espectro",
    "charts": "Gráficos",
    "tables": "Tabelas",
    "logs": "Logs",
    "eis": "EIS",
    "cycling": "Ciclagem",
    "circuits": "Circuitos",
    "drt": "DRT",
    "drt_peaks": "DRT Peaks",
    "drt_eis": "DRT + EIS",
    "rank_vs_retention": "Rank vs Retenção",
    "nyquist": "Nyquist",
    "bode": "Bode",
    "pca_2d": "PCA 2D",
    "pca_retention": "PCA Retenção",
    "correlation": "Correlação",
    "series": "Séries",
    "energy_power": "Energia × Potência",
    "ragone": "Ragone",
    "energy_vs_cycle": "Energia vs Ciclo",
    "retention_vs_cycle": "Retenção vs Ciclo",
    "heatmap_z": "Heatmap |Z|",
    "box_plot": "Box-plot",
    "radar": "Radar",
    "drt_x_eis": "DRT × EIS",
    "filter": "Filtro:",
    "sample": "Amostra:",
    "file": "Arquivo:",
    "highlight": "Destaque:",
    "metric": "Métrica:",
    "column": "Coluna:",
    "series_label": "Série:",
    "mode": "Modo:",
    "overlay_comma": "Overlay (vírgula):",
    "samples_sep": "Amostras (separe por ';'):",
    "rows_count": "Linhas: 0/0",
    "none": "— nenhum —",
    "save_image": "Salvar imagem",
    "save_filtered": "Salvar filtrado",
    "save_all": "Salvar tudo",
    "save_chart": "Salvar gráfico",
    "apply_overlay": "Aplicar overlay",
    "update": "Atualizar",
    "save_visual": "Salvar visual",
    "view_interactive": "Ver interativo",
    "top_5": "Top 5",
    "all": "Todos",
    "search_all_columns": "Buscar em todas as colunas",
    "status_ready": "Status: pronto",
    "ready": "Pronto",
    "subclass": "Subclasse",
    "samples": "Amostras",
    "all_fem": "Todas",
    "generate_pdf": "Gerar Relatório PDF",
    "ai_analysis": "Análise IA",
    "settings": "Configurações",
    "export_pdf": "Exportar PDF",
    "cancel": "Cancelar",
    "close": "Fechar",
    "run": "Executar",
    "select_language": "Selecionar idioma",
    "language_changed": "Idioma alterado para {lang}",
    "restart_required": "Reinicie para aplicar as alterações de idioma"
  },

  "pipeline": {
    "running_eis": "rodando EIS",
    "running_cycling": "rodando Ciclagem",
    "running_both": "rodando ambos",
    "running_drt": "rodando DRT",
    "error_eis": "erro no EIS",
    "error_cycling": "erro na Ciclagem",
    "error_both": "erro ao rodar ambos",
    "error_drt": "erro no DRT",
    "eis_complete": "EIS concluído",
    "cycling_complete": "Ciclagem concluída",
    "both_complete": "Ambos concluídos",
    "drt_complete": "DRT concluído",
    "identifying_eis": "Identificando amostras EIS...",
    "calculating_eis": "Calculando valores EIS...",
    "generating_tables_charts": "Gerando tabelas e gráficos...",
    "identifying_cycles": "Identificando ciclos...",
    "calculating_energy": "Calculando valores de energia...",
    "generating_charts_tables": "Gerando gráficos e tabelas...",
    "identifying_eis_cycles": "Identificando dados EIS e ciclos...",
    "calculating_eis_short": "Calculando EIS...",
    "calculating_cycling": "Calculando ciclagem...",
    "calculating_drt": "Calculando DRT...",
    "running_drt_inversion": "Executando inversão DRT...",
    "organizing_drt_results": "Organizando resultados DRT...",
    "error": "Erro",
    "kmeans_efficient": "Interface eficiente",
    "kmeans_stable": "Genérica estável",
    "kmeans_undefined_no_fit": "Indefinida (sem ajuste físico)",
    "kmeans_undefined_insuf": "Indefinida (dados insuficientes)",
    "kmeans_undefined_fail": "Indefinida (fit falhou)",
    "batch_processing": "Processamento em lote",
    "batch_complete": "Processamento concluído: {succeeded}/{total} ficheiros ({rate}%)",
    "batch_cancelled": "Processamento cancelado"
  },

  "ai": {
    "executive_summary": "Resumo Executivo",
    "findings": "Achados",
    "anomalies": "Anomalias",
    "recommendations": "Recomendações",
    "predictions": "Previsões",
    "quality_excellent": "Qualidade geral: EXCELENTE",
    "quality_good": "Qualidade geral: BOA",
    "quality_moderate": "Qualidade geral: MODERADA",
    "quality_critical": "Qualidade geral: CRÍTICA — atenção necessária.",
    "total_recommendations": "Total de {n} recomendação(ões), sendo {h} de alta prioridade.",
    "rp_negative": "Rp negativo na amostra '{idx}' — fitting pode não ter convergido.",
    "rs_negative": "Rs negativo na amostra '{idx}' — possível artefato ou fitting falho.",
    "cpe_out_of_range": "CPE exponent fora de [0, 1] — fitting não-físico.",
    "rs_cv_high": "CV de Rs = {cv:.1f}% — alta variabilidade entre amostras.",
    "rs_low_power_low": "Rs baixo ({rs:.2f} Ω) mas potência baixa ({p:.1f} µW) — gargalo pode ser difusão.",
    "retention_low_rp_mod": "Retenção baixa ({ret:.1f}%) com Rp moderado ({rp:.2f} Ω) — sugere degradação mecânica.",
    "sigma_high_drt_slow": "Sigma alto ({sigma:.2f}) e pico DRT lento ({tau:.4f} s) — sistema dominado por difusão.",
    "rs_high_energy_low": "Rs elevado ({rs:.2f} Ω) com energia baixa — a resistência ôhmica é provavelmente o principal limitante.",
    "energy_estimated": "Energia estimada ≈ {val:.1f} µJ (proporcional a C_mean).",
    "power_estimated": "Potência estimada ≈ {val:.1f} µW (inversamente proporcional a Rs).",
    "retention_estimated": "Retenção estimada ≈ {val:.1f}%.",
    "prediction_heuristic": "Predição baseada em regras heurísticas (sem histórico ML suficiente).",
    "prediction_ml": "Predição baseada em modelo ML treinado com {n} amostras.",
    "important_features": "Features mais importantes: {features}.",
    "rs_increased": "Rs aumentou {pct:.0f}% — sugere crescimento de filme passivo ou degradação de contato.",
    "c_decreased": "C_mean diminuiu {pct:.0f}% — sugere perda de material ativo ou desativação de sítios.",
    "contact_degradation": "Rs +{rs_pct:.0f}% e n {n_pct:.0f}% — possível degradação de contato elétrico.",
    "sigma_increased": "Sigma aumentou {pct:.0f}% — possível degradação do eletrólito ou bloqueio de poros.",
    "no_significant_degradation": "Sem degradação significativa detectada.",
    "subtle_changes": "Mudanças sutis detectadas sem mecanismo dominante claro.",
    "primary_mechanism": "Mecanismo primário identificado com contribuições secundárias.",
    "inconclusive": "Análise de degradação inconclusiva.",
    "no_eis_data": "Sem dados EIS disponíveis para predição.",
    "insufficient_eis": "Dados EIS insuficientes para análise de degradação.",
    "reduce_rs": "Reduzir resistência ôhmica: polir eletrodo, usar cola de prata ou pasta condutora.",
    "reduce_rs_impact": "Esperada redução de Rs em 30-60%, melhoria na potência.",
    "electrolyte_more_conductive": "Considerar eletrólito mais condutivo (ex.: H₂SO₄ vs Na₂SO₄).",
    "increase_active_area": "Aumentar área eletroativa: otimizar deposição, usar substrato poroso.",
    "optimize_morphology": "Otimizar morfologia: controlar taxa de deposição, temperatura e tempo.",
    "reduce_potential_window": "Reduzir janela de potencial para melhorar estabilidade cíclica.",
    "no_data_for_analysis": "Nenhum dado fornecido para análise."
  },

  "reports": {
    "title_default": "IonFlow Pipeline - Relatório de Análise",
    "subtitle_default": "Espectroscopia de Impedância Eletroquímica",
    "summary": "Resumo",
    "circuit_justification": "Justificação do Circuito",
    "parameter_interpretation": "Interpretação dos Parâmetros",
    "fit_quality": "Qualidade do Ajuste",
    "recommendations": "Recomendações",
    "comparison_similar": "Comparação com Amostras Anteriores",
    "executive_summary": "Resumo Executivo",
    "eis_analysis": "Análise de Impedância EIS",
    "cycling_analysis": "Análise de Ciclagem",
    "drt_analysis": "Análise DRT",
    "correlations": "Correlações",
    "ai_interpretation": "Interpretação IA",
    "references": "Referências",
    "eis_not_performed": "A análise EIS não foi realizada.",
    "cycling_not_performed": "A análise de ciclagem não foi realizada.",
    "drt_not_performed": "A análise DRT não foi realizada.",
    "insuf_correlation": "Dados insuficientes para análise de correlação.",
    "no_numeric_cols": "Colunas numéricas insuficientes para correlação.",
    "top_correlations": "Principais correlações Spearman (|ρ| > 0.5):",
    "no_strong_corr": "Nenhuma correlação forte encontrada (|ρ| > 0.5).",
    "param_rs": "resistência ôhmica do eletrólito",
    "param_rp": "resistência de transferência de carga",
    "param_q": "pseudo-capacitância CPE",
    "param_n": "expoente CPE — dispersão da constante de tempo",
    "param_sigma": "coeficiente de Warburg",
    "param_c": "capacitância ideal da dupla camada",
    "param_l": "indutância em série",
    "param_rd": "resistência de difusão",
    "param_tau_d": "constante de tempo de difusão",
    "rs_low": "valor baixo, típico de eletrólito concentrado",
    "rs_moderate": "valor moderado — pode limitar a potência",
    "rs_high": "valor alto — possível problema de contato ou eletrólito diluído",
    "rp_low": "cinética rápida — bom desempenho eletroquímico",
    "rp_moderate": "cinética moderada — desempenho aceitável",
    "rp_high": "cinética lenta — possível barreira de transferência de carga",
    "n_ideal": "comportamento quase ideal (capacitor puro)",
    "n_good": "rugosidade ou porosidade moderada",
    "n_moderate": "dispersão significativa — superfície heterogénea",
    "n_poor": "forte dispersão, superfície muito heterogénea",
    "sigma_low": "difusão rápida — sistema não limitado por transporte de massa",
    "sigma_moderate": "difusão contribui significativamente",
    "sigma_high": "difusão é o principal gargalo",
    "circuit_fitted": "O circuito **{name}** ({diagram}) foi ajustado com {method}.",
    "typical_systems": "Sistemas típicos: {systems}.",
    "ranked_position": "Classificado em {rank}º lugar entre {total} candidatos.",
    "strong_evidence": "forte evidência a favor",
    "moderate_evidence": "evidência moderada",
    "selected_bic_aic": "selecionado com base nos critérios BIC/AIC",
    "optimizer_not_converged": "O optimizador não convergiu — considerar ajustar bounds ou seed inicial.",
    "residuals_structured": "Os resíduos são estruturados — o modelo pode não capturar um processo.",
    "nrss_high": "O RSS normalizado é elevado — ajuste de qualidade questionável.",
    "fit_excellent": "O ajuste está excelente — resíduos baixos e não-estruturados.",
    "no_history": "Sem dados históricos para comparação.",
    "history_unavailable": "Histórico indisponível.",
    "higher": "maior",
    "lower": "menor",
    "generated_on": "Gerado em {date}",
    "page": "Página {n}"
  },

  "columns": {
    "frequency": "Frequência",
    "zreal": "Z' (Ω)",
    "zimag": "-Z'' (Ω)",
    "sample": "Amostra",
    "subclass": "Subclasse",
    "score": "Score",
    "rank": "Rank",
    "circuit": "Circuito",
    "retention_pct": "Retenção (%)",
    "energy_wh_kg": "Energia (Wh/kg)",
    "power_w_kg": "Potência (W/kg)",
    "energy_uj": "Energia (µJ)",
    "power_uw": "Potência (µW)",
    "cycles": "Ciclos",
    "cycle": "Ciclo",
    "c_spec": "C_espec (F/g)",
    "mean": "Média",
    "std": "Desvio padrão",
    "cv": "CV (%)"
  },

  "plots": {
    "zreal_axis": "Z′ (Ω)",
    "zimag_axis": "−Z″ (Ω)",
    "frequency_axis": "Frequência (Hz)",
    "impedance_axis": "|Z| (Ω)",
    "phase_axis": "Fase (°)",
    "energy_axis": "Energia (Wh/kg)",
    "power_axis": "Potência (W/kg)",
    "cycle_axis": "Ciclo",
    "n_cycles_axis": "Número de Ciclos",
    "retention_axis": "Retenção (%)",
    "sample_axis": "Amostra",
    "component_axis": "Componente",
    "variance_explained": "Variância explicada (%)",
    "value_axis": "Valor",
    "selected": "Selecionada",
    "data": "Dados",
    "fit": "Ajuste",
    "z_data": "|Z| dados",
    "z_fit": "|Z| ajuste",
    "phase_data": "Fase dados",
    "phase_fit": "Fase ajuste",
    "ragone_title": "Ragone Plot",
    "nyquist_overlay": "Nyquist — Dados vs Ajuste",
    "heatmap_title": "Heatmap de Impedância — log₁₀|Z|",
    "radar_title": "Radar — Comparação de Métricas",
    "retention_vs_cycle": "Retenção vs Ciclo",
    "rank_vs_retention": "Rank vs Retenção",
    "correlation_title": "Correlação (Spearman)",
    "pca_2d_metric": "PCA 2D (métrica contínua)",
    "boxplot_title": "Box-plot de {col}",
    "prefix_numeric": "Prefixo numérico",
    "drt_overlay": "DRT Overlay",
    "drt_heatmap": "DRT Heatmap",
    "gamma_axis": "γ(τ) [Ω]",
    "tau_axis": "τ (s)",
    "no_drt_data": "Sem dados DRT",
    "residual_real": "Resíduo — Parte Real",
    "residual_imag": "Resíduo — Parte Imaginária",
    "residuals_vs_freq": "Resíduos vs Frequência",
    "residual_histogram": "Histograma de Resíduos",
    "qq_plot": "QQ-Plot dos Resíduos",
    "theoretical_quantiles": "Quantis Teóricos",
    "sample_quantiles": "Quantis Amostrais (Ω)",
    "model_comparison_bic": "Comparação de Modelos — BIC",
    "confidence_softmax": "Confiança (softmax)",
    "relative_confidence": "Confiança Relativa",
    "watermark": "IonFlow Pipeline",
    "cycling_curves": "Curvas de Ciclagem",
    "energy_per_cycle": "Energia por Ciclo"
  },

  "diagnostics": {
    "fit_excellent": "Fit excelente",
    "fit_acceptable": "Fit aceitável",
    "fit_problematic": "Fit problemático",
    "nrss_low": "RSS normalizado baixo",
    "nrss_moderate": "RSS normalizado moderado",
    "nrss_high": "RSS normalizado alto",
    "residuals_structured": "Resíduos estruturados (autocorrelação lag-1 = {val:.2f})",
    "residuals_ok": "Resíduos não-estruturados",
    "bound_hits": "{n} parâmetros nos limites (bound hits)",
    "near_bounds": "{n} parâmetros próximos dos limites",
    "no_bound_hits": "Nenhum parâmetro nos limites",
    "optimizer_not_converged": "Optimizador não convergiu completamente"
  },

  "cli": {
    "description": "IonFlow Pipeline — EIS analytics toolkit",
    "eis_complete": "EIS pipeline completo — {n} ficheiros processados",
    "cycling_complete": "Ciclagem completa — {n} ficheiros processados",
    "drt_complete": "DRT pipeline completo — {n} ficheiros processados",
    "output_json": "Resultado de saída como JSON",
    "no_config_action": "Nenhuma ação de configuração especificada.",
    "valid": "Válido",
    "invalid": "Inválido",
    "errors": "Erros",
    "help_data_dir": "Diretório com os ficheiros de dados",
    "help_config": "Caminho para o ficheiro de configuração JSON",
    "help_output": "Diretório de saída para resultados",
    "help_scan_rate": "Taxa de varrimento (A/g)",
    "help_lambda": "Parâmetro de regularização DRT",
    "help_n_taus": "Número de constantes de tempo DRT",
    "help_language": "Idioma de saída (pt, en, es)",
    "help_json": "Saída em formato JSON",
    "help_ai": "Ativar análise por agente IA",
    "help_export_pdf": "Exportar relatório PDF"
  },

  "empty": {
    "no_data": "Nenhum dado disponível.",
    "no_rank_retention": "Sem dados para Rank vs Retenção",
    "no_eis_data": "Sem dados EIS disponíveis",
    "no_pca_data": "Sem dados de PCA",
    "no_pca_retention": "Sem dados de PCA/Retenção",
    "no_correlation_data": "Sem dados suficientes para correlação",
    "no_drt_eis": "Sem dados combinados DRT+EIS",
    "no_cycling_data": "Sem dados de ciclagem disponíveis",
    "no_cycle_sample": "Sem dados de ciclos para esta amostra",
    "no_ragone_data": "Sem dados para Ragone",
    "no_cycling_ragone": "Sem dados de ciclagem para Ragone",
    "no_cycling_metrics": "Sem métricas de ciclagem",
    "no_eis_heatmap": "Sem dados EIS para heatmap",
    "heatmap_failed": "Não foi possível gerar heatmap",
    "no_numeric_boxplot": "Sem métricas numéricas para box-plot",
    "no_eis_boxplot": "Sem dados EIS para box-plot",
    "need_2_samples_radar": "Precisa de ≥2 amostras para radar",
    "no_eis_radar": "Sem dados EIS para radar",
    "select_2_samples": "Selecione ao menos 2 amostras com ≥3 métricas numéricas",
    "no_retention_data": "Sem dados suficientes para retenção",
    "no_series_cols": "Sem colunas de série disponíveis",
    "no_series_id": "Sem séries identificadas",
    "no_series_data": "Sem dados de séries disponíveis",
    "no_drt_results": "Sem resultados DRT disponíveis",
    "no_drt_data": "Sem dados DRT disponíveis",
    "no_data_short": "Sem dados disponíveis",
    "insuf_radar": "Dados insuficientes\npara radar"
  },

  "log": {
    "interactive_unavail": "Interativo não disponível para este gráfico.",
    "drt_reset": "DRT resetado para preset padrão (Balanceado).",
    "table_not_found": "Tabela não encontrada.",
    "no_data_to_save": "Nenhum dado para salvar.",
    "no_rank_retention_data": "Sem dados de rank vs retenção para exibir.",
    "rank_retention_missing": "Dados de Rank/Retenção ausentes.",
    "mplcursors_missing": "mplcursors não encontrado; hover desabilitado.",
    "no_pca_display": "Sem dados de PCA para exibir.",
    "no_correlation": "Sem dados para correlação.",
    "insuf_correlation": "Dados insuficientes para correlação.",
    "no_series_display": "Sem dados de séries para exibir.",
    "series_unrecognized": "Formato de série não reconhecido.",
    "no_series_points": "Sem pontos para esta série.",
    "no_drt_save": "Sem visual DRT para salvar.",
    "no_ep_save": "Nenhum gráfico EP para salvar."
  },

  "knowledge": {
    "rs_very_low": "Resistência ôhmica muito baixa — contato elétrico excelente.",
    "rs_low": "Resistência ôhmica baixa — eletrólito de alta condutividade.",
    "rs_moderate": "Resistência ôhmica moderadamente elevada — possível limitação na potência.",
    "rs_high": "Resistência ôhmica elevada — limitante significativo de desempenho.",
    "rp_very_low": "Resistência de transferência de carga muito baixa — cinética excepcional.",
    "rp_low": "Resistência de transferência de carga baixa — bom desempenho.",
    "rp_moderate": "Resistência de transferência de carga moderada.",
    "rp_high": "Resistência de transferência de carga alta — cinética lenta.",
    "n_ideal": "CPE exponent próximo de 1 — comportamento quase ideal.",
    "n_good": "CPE exponent alto — rugosidade ou porosidade moderada.",
    "n_moderate": "CPE exponent moderado — dispersão significativa.",
    "n_poor": "CPE exponent baixo — forte dispersão, superfície muito heterogénea.",
    "sigma_low": "Coeficiente de Warburg baixo — difusão rápida.",
    "sigma_moderate": "Coeficiente de Warburg moderado — difusão contribui significativamente.",
    "sigma_high": "Coeficiente de Warburg alto — difusão é o principal gargalo.",
    "polish_electrode": "Polir eletrodo ou usar cola de prata.",
    "check_cables": "Verificar blindagem dos cabos.",
    "review_raw_data": "Rever dados brutos."
  }
}
